variable_declaration_checker/__init__.py
variable_declaration_checker-0.0.7.dist-info/METADATA
variable_declaration_checker-0.0.7.dist-info/WHEEL
variable_declaration_checker-0.0.7.dist-info/top_level.txt
variable_declaration_checker-0.0.7.dist-info/RECORD
