Metadata-Version: 2.4
Name: variable_declaration_checker
Version: 0.0.7
Summary: A PyLint checker to force your variable to be declared, and not duplicately declared.
Author-email: yueyinqiu <yueyinqiu@outlook.com>
License: MIT License
Project-URL: Repository, https://github.com/yueyinqiu/variable_declaration_checker.git
Requires-Dist: pylint
